{
  "map": {
    "grid_size": 64,
    "start_pos": [
      1,
      62
    ],
    "goal_pos": [
      62,
      1
    ]
  },
  "enemies": [
    {
      "id": 1,
      "pos": [
        50,
        20
      ],
      "detection_shape": "circle",
      "comment": "",
      "detection_zones": [
        {
          "r": 4,
          "p": 0.95
        },
        {
          "r": 6,
          "p": 0.6
        },
        {
          "r": 8,
          "p": 0.3
        }
      ]
    },
    {
      "id": 2,
      "pos": [
        41,
        28
      ],
      "detection_shape": "circle",
      "comment": "",
      "detection_zones": [
        {
          "r": 4,
          "p": 0.95
        },
        {
          "r": 6,
          "p": 0.6
        },
        {
          "r": 8,
          "p": 0.3
        }
      ]
    },
    {
      "id": 3,
      "pos": [
        32,
        45
      ],
      "detection_shape": "circle",
      "comment": "",
      "detection_zones": [
        {
          "r": 4,
          "p": 0.95
        },
        {
          "r": 6,
          "p": 0.6
        },
        {
          "r": 8,
          "p": 0.3
        }
      ]
    },
    {
      "id": 4,
      "pos": [
        31,
        13
      ],
      "detection_shape": "circle",
      "comment": "",
      "detection_zones": [
        {
          "r": 4,
          "p": 0.95
        },
        {
          "r": 6,
          "p": 0.6
        },
        {
          "r": 8,
          "p": 0.3
        }
      ]
    },
    {
      "id": 5,
      "pos": [
        27,
        17
      ],
      "detection_shape": "circle",
      "comment": "",
      "detection_zones": [
        {
          "r": 4,
          "p": 0.95
        },
        {
          "r": 6,
          "p": 0.6
        },
        {
          "r": 8,
          "p": 0.3
        }
      ]
    },
    {
      "id": 6,
      "pos": [
        18,
        47
      ],
      "detection_shape": "circle",
      "comment": "",
      "detection_zones": [
        {
          "r": 4,
          "p": 0.95
        },
        {
          "r": 6,
          "p": 0.6
        },
        {
          "r": 8,
          "p": 0.3
        }
      ]
    },
    {
      "id": 7,
      "pos": [
        10,
        30
      ],
      "detection_shape": "circle",
      "comment": "",
      "detection_zones": [
        {
          "r": 4,
          "p": 0.95
        },
        {
          "r": 6,
          "p": 0.6
        },
        {
          "r": 8,
          "p": 0.3
        }
      ]
    }
  ]
}